pyqt_media_slider/__init__.py
pyqt_media_slider/mediaSlider.py
pyqt_media_slider/style/__init__.py
pyqt_media_slider/style/slider.css
pyqt_media_slider-0.0.13.dist-info/LICENSE
pyqt_media_slider-0.0.13.dist-info/METADATA
pyqt_media_slider-0.0.13.dist-info/WHEEL
pyqt_media_slider-0.0.13.dist-info/top_level.txt
pyqt_media_slider-0.0.13.dist-info/RECORD
