Metadata-Version: 2.1
Name: pyqt-media-slider
Version: 0.0.13
Summary: PyQt media slider
Home-page: https://github.com/yjg30737/pyqt-media-slider.git
Author: Jung Gyu Yoon
Author-email: yjg30737@gmail.com
License: MIT
License-File: LICENSE
Requires-Dist: PyQt5 (>=5.8)
Requires-Dist: pyqt-resource-helper (>=0.0.1)
